README.md
setup.cfg
setup.py
iprange/__init__.py
iprange/__main__.py
iprange/ipaddress.py
iprange.egg-info/PKG-INFO
iprange.egg-info/SOURCES.txt
iprange.egg-info/dependency_links.txt
iprange.egg-info/entry_points.txt
iprange.egg-info/top_level.txt