Metadata-Version: 1.0
Name: iprange
Version: 0.2.1
Summary: IP-Range generator
Home-page: https://github.com/philip-s/py_iprange
Author: Philip Stoop
Author-email: stoopphilip97@gmail.com
License: UNKNOWN
Platform: UNKNOWN
